unmessage/__init__.py
unmessage/__main__.py
unmessage/_version.py
unmessage/cli.py
unmessage/contact.py
unmessage/elements.py
unmessage/errors.py
unmessage/gui.py
unmessage/message.py
unmessage/notifications.py
unmessage/packets.py
unmessage/peer.py
unmessage/requests.py
unmessage/smp.py
unmessage/ui.py
unmessage/untalk.py
unmessage/utils.py
unmessage-0.2.0.dist-info/DESCRIPTION.rst
unmessage-0.2.0.dist-info/METADATA
unmessage-0.2.0.dist-info/RECORD
unmessage-0.2.0.dist-info/WHEEL
unmessage-0.2.0.dist-info/entry_points.txt
unmessage-0.2.0.dist-info/metadata.json
unmessage-0.2.0.dist-info/top_level.txt
