Metadata-Version: 2.0
Name: unmessage
Version: 0.2.0
Summary: Privacy enhanced instant messenger
Home-page: https://github.com/AnemoneLabs/unmessage
Author: Anemone Labs
Author-email: anemone@anemone.me
License: GPLv3
Keywords: messenger privacy anonimity pyaxo axolotl double ratchet tor
Platform: UNKNOWN
Classifier: Development Status :: 3 - Alpha
Classifier: Intended Audience :: Developers
Classifier: Intended Audience :: End Users/Desktop
Classifier: License :: OSI Approved :: GNU General Public License v3 (GPLv3)
Classifier: Operating System :: POSIX :: Linux
Classifier: Programming Language :: Python :: 2.7
Classifier: Topic :: Communications :: Chat
Requires-Dist: PyAudio (>=0.2.10)
Requires-Dist: PyNaCl (>=1.0.1)
Requires-Dist: Twisted[tls] (>=16.6.0)
Requires-Dist: opuslib (>=1.1.0)
Requires-Dist: pyaxo (>=0.7.3)
Requires-Dist: pyperclip (>=1.5.27)
Requires-Dist: txtorcon (>=0.19.0)
